[
    {
        "id": 0,
        "title": "Date: 6/13/19",
        "filename": "camping1.jpg",
        "location": "Location: "
    },
    {
        "id": 1,
        "title": "Date: 5/1/19",
        "filename": "camping2.jpg",
        "location": "Location: "
    },
    {
        "id": 2,
        "title": "Date: 7/13/19",
        "filename": "camping3.jpg",
        "location": "Location: "
    },
    {
        "id": 3,
        "title": "Date: 2/13/19",
        "filename": "camping4.jpg",
        "location": "Location: "
    },
    {
        "id": 4,
        "title": "Date: 3/13/19",
        "filename": "camping5.jpg",
        "location": "Location: "
    },
    {
        "id": 5,
        "title": "Date: 2/16/19",
        "filename": "fishing1.jpg",
        "location": "Location: "
    },
    {
        "id": 6,
        "title": "Date: 2/15/19",
        "filename": "fishing2.jpg",
        "location": "Location: "
    },
    {
        "id": 7,
        "title": "Date: 4/12/19",
        "filename": "fishing3.jpg",
        "location": "Location: "
    },
    {
        "id": 8,
        "title": "Date: 2/13/19",
        "filename": "beach2.jpg",
        "location": "Location: "
    }
]